<?xml version="1.0" encoding="utf-8"?>
<!DOCTYPE hibernate-mapping PUBLIC "-//Hibernate/Hibernate Mapping DTD 3.0//EN"
"http://hibernate.sourceforge.net/hibernate-mapping-3.0.dtd">
<!-- 
    Mapping file autogenerated by MyEclipse Persistence Tools
-->
<hibernate-mapping>
    <class name="com.syuesoft.sell.model.XsSellCarReserve" table="xs_sell_car_reserve">
        <id name="reserveId" type="java.lang.Integer">
            <column name="reserve_id" />
            <generator class="increment" />
        </id>
        <property name="reserveCode" type="java.lang.String">
            <column name="reserve_code" length="30" />
        </property>
        <property name="customId" type="java.lang.Integer">
            <column name="custom_id" />
        </property>
        <property name="enterpriseId" type="java.lang.Integer">
            <column name="enterprise_Id" />
        </property>
        <property name="xsCarId" type="java.lang.Integer">
            <column name="xs_car_id" />
        </property>
        <property name="stfIdPerson" type="java.lang.Integer">
            <column name="STF_ID_PERSON" />
        </property>
        <property name="reserveDete" type="java.lang.String">
            <column name="reserve_dete" length="30" />
        </property>
        <!--<property name="carBrand" type="java.lang.Integer">
            <column name="car_brand" />
        </property>
        --><property name="carModel" type="java.lang.Integer">
            <column name="car_model" />
        </property>
        <!--<property name="carColor" type="java.lang.Integer">
            <column name="car_color" />
        </property>
        --><!--<property name="carTrim" type="java.lang.Integer">
            <column name="car_trim" />
        </property>
        --><!--<property name="carOutputVolume" type="java.lang.Integer">
            <column name="car_outputVolume" />
        </property>
        --><property name="limitLoadNum" type="java.lang.Integer">
            <column name="limit_load_num" />
        </property>
        <property name="pactCode" type="java.lang.String">
            <column name="pact_code" length="20" />
        </property>
        <!--<property name="customProperty" type="java.lang.Integer">
            <column name="custom_property" />
        </property>
        --><property name="paymentMoney" type="java.lang.Double">
            <column name="payment_money" precision="12" />
        </property><!--
        <property name="payWay" type="java.lang.Integer">
            <column name="pay_way" />
        </property>
        --><property name="sellingprice" type="java.lang.Double">
            <column name="sellingprice" precision="12" />
        </property>
        <!--<property name="examine" type="java.lang.Integer">
            <column name="examine" />
        </property>
        --><!--<property name="orderState" type="java.lang.Integer">
            <column name="order_state" />
        </property>
        --><property name="predictTakeDate" type="java.lang.String">
            <column name="predict_take_date" length="30" />
        </property>
        <property name="stfId" type="java.lang.Integer">
            <column name="STF_ID" />
        </property>
        <property name="xsDistributorCode" type="java.lang.String">
            <column name="xs_distributor_code" length="20" />
        </property>
        <property name="level" type="java.lang.Integer">
            <column name="level" />
        </property>
        <property name="firstPayMoney" type="java.lang.Double">
            <column name="first_pay_money" precision="12" />
        </property>
        <property name="loanBank" type="java.lang.Integer">
            <column name="loan_bank" />
        </property>
        <property name="loanLimitMoney" type="java.lang.Double">
            <column name="loan_limit_money" precision="12" />
        </property>
        <property name="loanLimitYear" type="java.lang.Double">
            <column name="loan_limit_year" precision="2" scale="1" />
        </property>
        <property name="vinCode" type="java.lang.String">
            <column name="vin_code" length="30" />
        </property>
        <property name="customOpinion" type="java.lang.String">
            <column name="custom_opinion" length="100" />
        </property>
        <property name="shingleMoney" type="java.lang.Double">
            <column name="shingle_money" precision="12" />
        </property>
        <property name="decorateMoney" type="java.lang.Double">
            <column name="decorate_money" precision="12" />
        </property>
        <property name="delState" type="java.lang.Integer">
            <column name="del_state" />
        </property>
        <property name="remark" type="java.lang.String">
            <column name="remark" length="200" />
        </property>
        <property name="mobilephone" type="java.lang.String">
            <column name="mobilephone" length="30" />
        </property>
        <property name="useNature" type="java.lang.Integer">
            <column name="use_nature" />
        </property>
		<many-to-one name="xsChilddictionary" class="com.syuesoft.sell.model.XsChilddictionary" lazy="false" fetch="select">
            <column name="car_brand" precision="11" />
        </many-to-one>
        <many-to-one name="xsChilddictionary1" class="com.syuesoft.sell.model.XsChilddictionary" lazy="false" fetch="select">
            <column name="car_color" precision="11" />
        </many-to-one>
        <many-to-one name="xsChilddictionary2" class="com.syuesoft.sell.model.XsChilddictionary" lazy="false" fetch="select">
            <column name="car_trim" precision="11" />
        </many-to-one>
        <many-to-one name="xsChilddictionary3" class="com.syuesoft.sell.model.XsChilddictionary" lazy="false" fetch="select">
            <column name="car_outputVolume" precision="11" />
        </many-to-one>
        <many-to-one name="xsChilddictionary4" class="com.syuesoft.sell.model.XsChilddictionary" lazy="false" fetch="select">
            <column name="custom_property" precision="11" />
        </many-to-one>
        <many-to-one name="xsChilddictionary5" class="com.syuesoft.sell.model.XsChilddictionary" lazy="false" fetch="select">
            <column name="pay_way" precision="11" />
        </many-to-one>
        <many-to-one name="xsChilddictionary6" class="com.syuesoft.sell.model.XsChilddictionary" lazy="false" fetch="select">
            <column name="examine" precision="11" />
        </many-to-one>
        <many-to-one name="xsChilddictionary7" class="com.syuesoft.sell.model.XsChilddictionary" lazy="false" fetch="select">
            <column name="order_state" precision="11" />
        </many-to-one>
    </class>
</hibernate-mapping>
